tehran_stocks/__init__.py
tehran_stocks/initializer.py
tehran_stocks/config/__init__.py
tehran_stocks/config/engine.py
tehran_stocks/download/__init__.py
tehran_stocks/download/names.py
tehran_stocks/download/price.py
tehran_stocks/models/__init__.py
tehran_stocks/models/create.py
tehran_stocks/models/stocks.py
tehran_stocks_ng-0.6.4.data/scripts/ts-get
tehran_stocks_ng-0.6.4.data/scripts/ts-get.bat
tehran_stocks_ng-0.6.4.dist-info/LICENSE
tehran_stocks_ng-0.6.4.dist-info/METADATA
tehran_stocks_ng-0.6.4.dist-info/WHEEL
tehran_stocks_ng-0.6.4.dist-info/top_level.txt
tehran_stocks_ng-0.6.4.dist-info/RECORD
