Metadata-Version: 2.1
Name: tehran-stocks-ng
Version: 0.6.4
Summary: Data Downloader for Tehran stock market
Home-page: http://github.com/gr8linux/tehran-stocks
Author: Mehdi Ghodsizadeh,gr8linux
Author-email: mehdi.ghodsizadeh@gmail.com
License: MIT
Platform: UNKNOWN
Requires-Python: >=3.6
Requires-Dist: wheel
Requires-Dist: pandas
Requires-Dist: sqlalchemy
Requires-Dist: requests
